<?xml version="1.0" encoding="utf-8" ?>
<dwsync>
<file name="AdminLTE-bootstrap-social.css" server="G:/xampp/htdocs/ptangney/" local="131367921260000000" remote="131367921260000000" Dst="2" />
<file name="AdminLTE-bootstrap-social.min.css" server="G:/xampp/htdocs/ptangney/" local="131367921260000000" remote="131367921260000000" Dst="2" />
<file name="AdminLTE-fullcalendar.css" server="G:/xampp/htdocs/ptangney/" local="131367921260000000" remote="131367921260000000" Dst="2" />
<file name="AdminLTE-fullcalendar.min.css" server="G:/xampp/htdocs/ptangney/" local="131367921260000000" remote="131367921260000000" Dst="2" />
<file name="AdminLTE-select2.css" server="G:/xampp/htdocs/ptangney/" local="131367921260000000" remote="131367921260000000" Dst="2" />
<file name="AdminLTE-select2.min.css" server="G:/xampp/htdocs/ptangney/" local="131367921260000000" remote="131367921260000000" Dst="2" />
<file name="AdminLTE-without-plugins.css" server="G:/xampp/htdocs/ptangney/" local="131367921260000000" remote="131367921260000000" Dst="2" />
<file name="AdminLTE-without-plugins.min.css" server="G:/xampp/htdocs/ptangney/" local="131367921260000000" remote="131367921260000000" Dst="2" />
</dwsync>